config/__init__.py
config/models_config.yaml
rilaas/Client.py
rilaas/__init__.py
rilaas/get_file_type.py
rilaas/test.py
rilaas-0.2.2.dist-info/LICENSE
rilaas-0.2.2.dist-info/METADATA
rilaas-0.2.2.dist-info/WHEEL
rilaas-0.2.2.dist-info/top_level.txt
rilaas-0.2.2.dist-info/RECORD
