Metadata-Version: 2.1
Name: rilaas
Version: 0.2.2
Summary: This is a package for getting a response from the EC2 server for the models deployed for ServeLine
Home-page: https://github.com/ahfahad96/rilaas
Author: Abdul Hafeez Fahad
Author-email: ah.fahad@redbuffer.net
License: MIT
License-File: LICENSE
Requires-Dist: requests
Requires-Dist: pyyaml
Requires-Dist: requests-toolbelt
